codefeedback/__init__.py
codefeedback/codeval.py
codefeedback/checks/__init__.py
codefeedback/checks/ai_checks.py
codefeedback/checks/general_check.py
codefeedback/checks/global_variable_check.py
codefeedback/checks/local_variable_check.py
codefeedback/checks/same_variable_content_check.py
codefeedback/checks/structure_check.py
codefeedback/format/__init__.py
codefeedback/format/compare_format.py
codefeedback/format/display_message_format.py
codefeedback/format/general_format.py
codefeedback/format/output_traceback_format.py
codefeedback/mevars/__init__.py
codefeedback/mevars/configs.py
codefeedback/mevars/globals.py
codefeedback/mevars/stats.py
codefeedback/utils/__init__.py
codefeedback/utils/file_utils.py
codefeedback/utils/method_utils.py
codefeedback/utils/module_utils.py
codefeedback/utils/param_utils.py
codefeedback/utils/plt_manage_utils.py
codefeedback-0.3.0.dist-info/METADATA
codefeedback-0.3.0.dist-info/WHEEL
codefeedback-0.3.0.dist-info/top_level.txt
codefeedback-0.3.0.dist-info/RECORD
